zschema/__init__.py
zschema/__main__.py
zschema/compounds.py
zschema/example.py
zschema/keys.py
zschema/leaves.py
zschema/registry.py
zschema/test_zschema.py
zschema-0.11.0.dist-info/LICENSE
zschema-0.11.0.dist-info/METADATA
zschema-0.11.0.dist-info/WHEEL
zschema-0.11.0.dist-info/entry_points.txt
zschema-0.11.0.dist-info/top_level.txt
zschema-0.11.0.dist-info/RECORD
